dbpystream/__init__.py
dbpystream/api.py
dbpystream/client.py
dbpystream/run_test.py
dbpystream/utils.py
dbpystream/version.py
test/__init__.py
test/test.py
dbpystream-1.1.dist-info/LICENSE
dbpystream-1.1.dist-info/METADATA
dbpystream-1.1.dist-info/WHEEL
dbpystream-1.1.dist-info/top_level.txt
dbpystream-1.1.dist-info/RECORD
