Metadata-Version: 2.1
Name: dbpystream
Version: 1.1
Home-page: https://github.com/songroom2016/dbpystream.git
Author: songroom
Author-email: rustroom@163.com
License: Apache
Classifier: License :: OSI Approved :: Apache Software License
Classifier: Natural Language :: English
Classifier: Operating System :: OS Independent
Classifier: Programming Language :: Python
Classifier: Programming Language :: Python :: 3.6
Classifier: Topic :: Software Development :: Libraries :: Python Modules
Requires-Python: >=3.6
License-File: LICENSE
Requires-Dist: pandas >=0.18.0
Requires-Dist: requests >=2.0.0
Requires-Dist: toml >=0.10
Requires-Dist: pyzstd >=0.15
Requires-Dist: numpy >=1.9.2
